yamlprocessor/__init__.py
yamlprocessor/datapreprocessor.py
yamlprocessor/dataprocess.py
yamlprocessor/schemaprocess.py
yamlprocessor/tests/__init__.py
yamlprocessor/tests/test_datapreprocess.py
yamlprocessor/tests/test_dataprocess.py
yamlprocessor/tests/test_schemaprocess.py
yamlprocessor-0.6.7.dist-info/licenses/LICENSE
yamlprocessor-0.6.7.dist-info/METADATA
yamlprocessor-0.6.7.dist-info/WHEEL
yamlprocessor-0.6.7.dist-info/entry_points.txt
yamlprocessor-0.6.7.dist-info/top_level.txt
yamlprocessor-0.6.7.dist-info/RECORD
