Metadata-Version: 2.4
Name: yamlprocessor
Version: 0.6.7
Summary: Process values in YAML files
Maintainer-email: Matt Shin <matthew.shin@metoffice.gov.uk>
License: BSD 3-Clause License
Project-URL: Homepage, https://github.com/JCSDA-internal/yamlprocessor/
Project-URL: Bug Reports, https://github.com/JCSDA-internal/yamlprocessor/issues
Project-URL: Source, https://github.com/JCSDA-internal/yamlprocessor/
Classifier: Development Status :: 5 - Production/Stable
Classifier: Intended Audience :: Science/Research
Classifier: Intended Audience :: Developers
Classifier: License :: OSI Approved :: BSD License
Classifier: Operating System :: OS Independent
Classifier: Programming Language :: Python :: 3
Classifier: Programming Language :: Python :: 3.9
Classifier: Programming Language :: Python :: 3.10
Classifier: Programming Language :: Python :: 3.11
Classifier: Programming Language :: Python :: 3.12
Classifier: Programming Language :: Python :: 3.13
Classifier: Programming Language :: Python :: 3 :: Only
Classifier: Topic :: Scientific/Engineering
Classifier: Topic :: Software Development
Requires-Python: >=3.9
License-File: LICENSE
Requires-Dist: jmespath
Requires-Dist: jsonschema
Requires-Dist: python-dateutil
Requires-Dist: ruamel.yaml
Provides-Extra: test
Requires-Dist: flake8; extra == "test"
Requires-Dist: pytest; extra == "test"
Requires-Dist: pytest-cov; extra == "test"
Dynamic: license-file
